setup.py
remorse/__init__.py
remorse/morse.py
remorse/wavegen.py
remorse.egg-info/PKG-INFO
remorse.egg-info/SOURCES.txt
remorse.egg-info/dependency_links.txt
remorse.egg-info/requires.txt
remorse.egg-info/top_level.txt
scripts/remorse