Metadata-Version: 1.0
Name: remorse
Version: 0.4
Summary: Morse code player
Home-page: http://github.com/jhobbs/remorse
Author: Jason Hobbs
Author-email: jason.hobbs@gmail.com
License: Apache License 2.0
Platform: UNKNOWN
